forecastflow/__init__.py
forecastflow/_auth.py
forecastflow/_storage.py
forecastflow/api/__init__.py
forecastflow/api/_v3.py
forecastflow/config.py
forecastflow/config.toml
forecastflow/data_source.py
forecastflow/enums.py
forecastflow/exceptions.py
forecastflow/model.py
forecastflow/prediction.py
forecastflow/project.py
forecastflow/satellite/__init__.py
forecastflow/satellite/google/__init__.py
forecastflow/satellite/google/cloud/__init__.py
forecastflow/satellite/google/cloud/storage.py
forecastflow/satellite/tableau/__init__.py
forecastflow/satellite/tableau/prep/__init__.py
forecastflow/satellite/tableau/prep/schema.py
forecastflow/satellite/tableau/prep/type.py
forecastflow/tabpy_support/__init__.py
forecastflow/tabpy_support/prep_schema.py
forecastflow/tabpy_support/prep_type.py
forecastflow/training.py
forecastflow/user.py
forecastflow/util.py
forecastflow-4.4.5.dist-info/METADATA
forecastflow-4.4.5.dist-info/WHEEL
forecastflow-4.4.5.dist-info/RECORD
